{
    "version": "1.2.0",
    "description": "A simple, fast cross-platform Markdown viewer and editor.",
    "homepage": "https://github.com/mdferdousalam/md-viewer",
    "license": "Freeware",
    "architecture": {
        "64bit": {
            "url": "https://github.com/mdferdousalam/md-viewer/releases/download/v1.2.0/Markdown-Viewer-1.2.0.exe#/md-viewer.exe",
            "hash": "9877e6a3e4b6732778caf1f5c2ccc2b019465f51f0c9d7482e65b0df7b565987"
        }
    },
    "bin": "md-viewer.exe",
    "shortcuts": [
        ["md-viewer.exe", "Markdown Viewer"]
    ],
    "checkver": "github",
    "autoupdate": {
        "architecture": {
            "64bit": {
                "url": "https://github.com/mdferdousalam/md-viewer/releases/download/v$version/Markdown-Viewer-$version.exe#/md-viewer.exe"
            }
        }
    }
}
